[
  {
    "id": "93b38c53-50a1-44ab-8b8e-28a72ee0e183",
    "firstName": "Test",
    "lastName": "Testerson",
    "email": "test@test.com",
    "password": "test123",
    "age": 40
  },
  {
    "id": "0bb58a7d-75e7-489b-bcde-988eec4dc47d",
    "firstName": "Best",
    "lastName": "Besterson",
    "email": "best@best.com",
    "password": "test123",
    "age": 43
  },
  {
    "id": "d18bda9f-5f07-4a2f-b2ed-5fa42c04c5f3",
    "firstName": "Bob",
    "lastName": "Bobsky",
    "email": "bob@gmail.com",
    "password": "changeMeOdma",
    "age": 25
  },
  {
    "id": "a73fb9de-6a9d-4703-84d3-cfd87e91dc6e",
    "firstName": "Jill",
    "lastName": "Wayne",
    "email": "jill@gmail.com",
    "password": "jill321",
    "age": 29
  }
]